azure/datalake/__init__.py
azure/datalake/store/__init__.py
azure/datalake/store/core.py
azure/datalake/store/enums.py
azure/datalake/store/exceptions.py
azure/datalake/store/lib.py
azure/datalake/store/multiprocessor.py
azure/datalake/store/multithread.py
azure/datalake/store/retry.py
azure/datalake/store/transfer.py
azure/datalake/store/utils.py
samples/__init__.py
samples/adal_test.py
samples/benchmarks.py
samples/cli.py
samples/gen2.py
samples/hung.py
samples/mp_temp.py
samples/psmlatency.py
samples/target_file_download.py
samples/temp.py
samples/temp1.py
samples/temp123.py
samples/temp2.py
azure_datalake_store-0.0.52.dist-info/License.txt
azure_datalake_store-0.0.52.dist-info/METADATA
azure_datalake_store-0.0.52.dist-info/WHEEL
azure_datalake_store-0.0.52.dist-info/top_level.txt
azure_datalake_store-0.0.52.dist-info/RECORD
