Metadata-Version: 1.1
Name: azure-datalake-store
Version: 0.0.52
Summary: Azure Data Lake Store Filesystem Client Library for Python
Home-page: https://github.com/Azure/azure-data-lake-store-python
Author: Microsoft Corporation
Author-email: ptvshelp@microsoft.com
License: MIT License
Keywords: azure
Platform: UNKNOWN
Classifier: Development Status :: 4 - Beta
Classifier: Programming Language :: Python
Classifier: Programming Language :: Python :: 2
Classifier: Programming Language :: Python :: 2.7
Classifier: Programming Language :: Python :: 3
Classifier: Programming Language :: Python :: 3.3
Classifier: Programming Language :: Python :: 3.4
Classifier: Programming Language :: Python :: 3.5
Classifier: Programming Language :: Python :: 3.6
Classifier: Programming Language :: Python :: 3.7
Classifier: License :: OSI Approved :: MIT License
